avogadro/AvogadroCalc.dll
avogadro/AvogadroCalc.lib
avogadro/AvogadroCore.dll
avogadro/AvogadroCore.lib
avogadro/AvogadroIO.dll
avogadro/AvogadroIO.lib
avogadro/AvogadroQuantumIO.dll
avogadro/AvogadroQuantumIO.lib
avogadro/__init__.py
avogadro/cjson.py
avogadro/connect.py
avogadro/core.cp312-win_arm64.pyd
avogadro/io.cp312-win_arm64.pyd
avogadro-1.102.0.data/data/include/avogadro/calc/avogadrocalcexport.h
avogadro-1.102.0.data/data/include/avogadro/calc/chargemanager.h
avogadro-1.102.0.data/data/include/avogadro/calc/chargemodel.h
avogadro-1.102.0.data/data/include/avogadro/calc/defaultmodel.h
avogadro-1.102.0.data/data/include/avogadro/calc/energycalculator.h
avogadro-1.102.0.data/data/include/avogadro/calc/energymanager.h
avogadro-1.102.0.data/data/include/avogadro/calc/gradients.h
avogadro-1.102.0.data/data/include/avogadro/calc/lennardjones.h
avogadro-1.102.0.data/data/include/avogadro/calc/uff.h
avogadro-1.102.0.data/data/include/avogadro/calc/uffdata.h
avogadro-1.102.0.data/data/include/avogadro/core/angleiterator.h
avogadro-1.102.0.data/data/include/avogadro/core/angletools.h
avogadro-1.102.0.data/data/include/avogadro/core/array.h
avogadro-1.102.0.data/data/include/avogadro/core/atom.h
avogadro-1.102.0.data/data/include/avogadro/core/atomtyper-inline.h
avogadro-1.102.0.data/data/include/avogadro/core/atomtyper.h
avogadro-1.102.0.data/data/include/avogadro/core/atomutilities.h
avogadro-1.102.0.data/data/include/avogadro/core/avogadrocore.h
avogadro-1.102.0.data/data/include/avogadro/core/avogadrocoreexport.h
avogadro-1.102.0.data/data/include/avogadro/core/basisset.h
avogadro-1.102.0.data/data/include/avogadro/core/bond.h
avogadro-1.102.0.data/data/include/avogadro/core/color3f.h
avogadro-1.102.0.data/data/include/avogadro/core/constraint.h
avogadro-1.102.0.data/data/include/avogadro/core/contrastcolor.h
avogadro-1.102.0.data/data/include/avogadro/core/coordinateblockgenerator.h
avogadro-1.102.0.data/data/include/avogadro/core/coordinateset.h
avogadro-1.102.0.dist-info/licenses/LICENSE
avogadro-1.102.0.dist-info/METADATA
avogadro-1.102.0.dist-info/WHEEL
avogadro-1.102.0.dist-info/top_level.txt
avogadro-1.102.0.dist-info/RECORD
