Metadata-Version: 2.4
Name: avogadro
Version: 1.102.0
Summary: Avogadro provides analysis and data processing useful in computational chemistry, molecular modeling, bioinformatics, materials science, and related areas.
Home-page: https://github.com/OpenChemistry/avogadrolibs
Author: Avogadro / OpenChemistry Developers
License: BSD
Project-URL: Documentation, https://two.avogadro.cc
Project-URL: Funding, https://github.com/sponsors/OpenChemistry
Project-URL: Source, https://github.com/OpenChemistry/avogadrolibs
Project-URL: Tracker, https://github.com/OpenChemistry/avogadrolibs/issues
Project-URL: Forum, https://discuss.avogadro.cc
Classifier: License :: OSI Approved :: BSD License
Classifier: Programming Language :: Python
Classifier: Programming Language :: C++
Classifier: Development Status :: 4 - Beta
Classifier: Development Status :: 5 - Production/Stable
Classifier: Intended Audience :: Developers
Classifier: Intended Audience :: Education
Classifier: Intended Audience :: Science/Research
Classifier: Topic :: Scientific/Engineering
Classifier: Topic :: Scientific/Engineering :: Chemistry
Classifier: Topic :: Scientific/Engineering :: Physics
Classifier: Topic :: Scientific/Engineering :: Visualization
Classifier: Topic :: Scientific/Engineering :: Information Analysis
Classifier: Topic :: Software Development :: Libraries
Classifier: Operating System :: Microsoft :: Windows
Classifier: Operating System :: Unix
Classifier: Operating System :: MacOS
License-File: LICENSE
Dynamic: author
Dynamic: classifier
Dynamic: description
Dynamic: description-content-type
Dynamic: home-page
Dynamic: license
Dynamic: license-file
Dynamic: project-url
Dynamic: summary
